[
    {
        "anonymous": false,
        "inputs": [
            {
                "components": [
                    {
                        "internalType": "address",
                        "name": "from",
                        "type": "address"
                    },
                    {
                        "internalType": "address",
                        "name": "to",
                        "type": "address"
                    },
                    {
                        "internalType": "string",
                        "name": "data",
                        "type": "string"
                    }
                ],
                "indexed": false,
                "internalType": "struct DChat.Message",
                "name": "m",
                "type": "tuple"
            }
        ],
        "name": "NewMessage",
        "type": "event"
    },
    {
        "inputs": [
            {
                "internalType": "string",
                "name": "_name",
                "type": "string"
            },
            {
                "internalType": "string",
                "name": "_pubKey",
                "type": "string"
            }
        ],
        "name": "registerUser",
        "outputs": [],
        "stateMutability": "nonpayable",
        "type": "function"
    },
    {
        "inputs": [
            {
                "internalType": "address",
                "name": "to",
                "type": "address"
            },
            {
                "internalType": "string",
                "name": "data",
                "type": "string"
            }
        ],
        "name": "sendMessage",
        "outputs": [],
        "stateMutability": "nonpayable",
        "type": "function"
    },
    {
        "inputs": [],
        "name": "fetchMessageCount",
        "outputs": [
            {
                "internalType": "uint256",
                "name": "",
                "type": "uint256"
            }
        ],
        "stateMutability": "view",
        "type": "function"
    },
    {
        "inputs": [],
        "name": "fetchMessages",
        "outputs": [
            {
                "components": [
                    {
                        "internalType": "address",
                        "name": "from",
                        "type": "address"
                    },
                    {
                        "internalType": "address",
                        "name": "to",
                        "type": "address"
                    },
                    {
                        "internalType": "string",
                        "name": "data",
                        "type": "string"
                    }
                ],
                "internalType": "struct DChat.Message[]",
                "name": "",
                "type": "tuple[]"
            }
        ],
        "stateMutability": "view",
        "type": "function"
    },
    {
        "inputs": [
            {
                "internalType": "address",
                "name": "to",
                "type": "address"
            }
        ],
        "name": "fetchPubKey",
        "outputs": [
            {
                "components": [
                    {
                        "internalType": "string",
                        "name": "uname",
                        "type": "string"
                    },
                    {
                        "internalType": "string",
                        "name": "pubKey",
                        "type": "string"
                    }
                ],
                "internalType": "struct DChat.UInfo",
                "name": "",
                "type": "tuple"
            }
        ],
        "stateMutability": "view",
        "type": "function"
    },
    {
        "inputs": [
            {
                "internalType": "address",
                "name": "user",
                "type": "address"
            }
        ],
        "name": "isRegistered",
        "outputs": [
            {
                "components": [
                    {
                        "internalType": "bool",
                        "name": "status",
                        "type": "bool"
                    },
                    {
                        "internalType": "string",
                        "name": "name",
                        "type": "string"
                    }
                ],
                "internalType": "struct DChat.RegCheck",
                "name": "",
                "type": "tuple"
            }
        ],
        "stateMutability": "view",
        "type": "function"
    },
    {
        "inputs": [
            {
                "internalType": "address",
                "name": "",
                "type": "address"
            }
        ],
        "name": "latest_timestamp",
        "outputs": [
            {
                "internalType": "uint256",
                "name": "",
                "type": "uint256"
            }
        ],
        "stateMutability": "view",
        "type": "function"
    },
    {
        "inputs": [
            {
                "internalType": "address",
                "name": "",
                "type": "address"
            },
            {
                "internalType": "uint256",
                "name": "",
                "type": "uint256"
            }
        ],
        "name": "messages",
        "outputs": [
            {
                "internalType": "address",
                "name": "from",
                "type": "address"
            },
            {
                "internalType": "address",
                "name": "to",
                "type": "address"
            },
            {
                "internalType": "string",
                "name": "data",
                "type": "string"
            }
        ],
        "stateMutability": "view",
        "type": "function"
    },
    {
        "inputs": [],
        "name": "n_users",
        "outputs": [
            {
                "internalType": "uint256",
                "name": "",
                "type": "uint256"
            }
        ],
        "stateMutability": "view",
        "type": "function"
    },
    {
        "inputs": [
            {
                "internalType": "address",
                "name": "",
                "type": "address"
            }
        ],
        "name": "pub_keys",
        "outputs": [
            {
                "internalType": "string",
                "name": "",
                "type": "string"
            }
        ],
        "stateMutability": "view",
        "type": "function"
    },
    {
        "inputs": [
            {
                "internalType": "address",
                "name": "",
                "type": "address"
            }
        ],
        "name": "users",
        "outputs": [
            {
                "internalType": "string",
                "name": "name",
                "type": "string"
            },
            {
                "internalType": "address",
                "name": "original",
                "type": "address"
            },
            {
                "internalType": "bool",
                "name": "reg",
                "type": "bool"
            },
            {
                "internalType": "uint256",
                "name": "n_msgs",
                "type": "uint256"
            }
        ],
        "stateMutability": "view",
        "type": "function"
    }
]